medium_stats/__init__.py
medium_stats/__main__.py
medium_stats/cli.py
medium_stats/cookie_fetcher.py
medium_stats/scraper.py
medium_stats/utils.py
medium_stats-2.1.2.dist-info/LICENSE
medium_stats-2.1.2.dist-info/METADATA
medium_stats-2.1.2.dist-info/WHEEL
medium_stats-2.1.2.dist-info/entry_points.txt
medium_stats-2.1.2.dist-info/top_level.txt
medium_stats-2.1.2.dist-info/RECORD
