Metadata-Version: 2.1
Name: medium-stats
Version: 2.1.2
Summary: CLI tool to fetch your Medium stats
Home-page: https://github.com/otosky/medium_stats
Author: Oliver Tosky
Author-email: olivertosky@gmail.com
License: GNU GPLv3
Keywords: Medium blog scraper analytics
Platform: UNKNOWN
Requires-Python: >=3.6
Requires-Dist: requests
Requires-Dist: lxml
Provides-Extra: selenium
Requires-Dist: selenium ; extra == 'selenium'
Requires-Dist: webdriver-manager ; extra == 'selenium'
